stenv/__init__.py
stenv/env.py
stenv-0.1.0.dist-info/licenses/LICENSE
stenv-0.1.0.dist-info/WHEEL
stenv-0.1.0.dist-info/METADATA
stenv-0.1.0.dist-info/RECORD
