Metadata-Version: 2.4
Name: stenv
Version: 0.1.0
Summary: A strongly typed environment variable management library for Python
Author-email: Author <author@example.com>
Requires-Python: >=3.10
Classifier: Programming Language :: Python :: 3
Classifier: Programming Language :: Python :: 3.12
Classifier: Programming Language :: Python :: 3.13
Classifier: License :: OSI Approved :: MIT License
Classifier: Operating System :: OS Independent
License-File: LICENSE
Requires-Dist: pytest-cov>=6.1.1
Project-URL: Bug Tracker, https://tangled.sh/@mint-tamas.bsky.social/stenv/issues
Project-URL: Homepage, https://tangled.sh/@mint-tamas.bsky.social/stenv
